xclim/__init__.py
xclim/analog.py
xclim/cli.py
xclim/sdba.py
xclim/core/__init__.py
xclim/core/_exceptions.py
xclim/core/_types.py
xclim/core/bootstrapping.py
xclim/core/calendar.py
xclim/core/cfchecks.py
xclim/core/datachecks.py
xclim/core/dataflags.py
xclim/core/formatting.py
xclim/core/indicator.py
xclim/core/locales.py
xclim/core/missing.py
xclim/core/options.py
xclim/core/units.py
xclim/core/utils.py
xclim/data/__init__.py
xclim/data/anuclim.yml
xclim/data/cf.yml
xclim/data/fr.json
xclim/data/icclim.yml
xclim/data/schema.yml
xclim/data/variables.yml
xclim/ensembles/__init__.py
xclim/ensembles/_base.py
xclim/ensembles/_filters.py
xclim/ensembles/_partitioning.py
xclim/ensembles/_reduce.py
xclim/ensembles/_robustness.py
xclim/indicators/__init__.py
xclim/indicators/atmos/__init__.py
xclim/indicators/atmos/_precip.py
xclim/indicators/atmos/_synoptic.py
xclim/indicators/atmos/_temperature.py
xclim/indicators/atmos/_wind.py
xclim/indicators/convert/__init__.py
xclim/indicators/convert/_conversion.py
xclim/indicators/generic/__init__.py
xclim/indicators/generic/_stats.py
xclim/indicators/land/__init__.py
xclim/indicators/land/_snow.py
xclim/indicators/land/_streamflow.py
xclim/indicators/seaIce/__init__.py
xclim/indicators/seaIce/_seaice.py
xclim/indices/__init__.py
xclim/indices/_agro.py
xclim/indices/_anuclim.py
xclim/indices/_conversion.py
xclim/indices/_hydrology.py
xclim/indices/_multivariate.py
xclim/indices/_simple.py
xclim/indices/_synoptic.py
xclim/indices/_threshold.py
xclim/indices/converters.py
xclim/indices/generic.py
xclim/indices/helpers.py
xclim/indices/run_length.py
xclim/indices/stats.py
xclim/indices/fire/__init__.py
xclim/indices/fire/_cffwis.py
xclim/indices/fire/_ffdi.py
xclim/testing/__init__.py
xclim/testing/conftest.py
xclim/testing/helpers.py
xclim/testing/registry.txt
xclim/testing/utils.py
xclim-0.60.0.dist-info/entry_points.txt
xclim-0.60.0.dist-info/licenses/LICENSE
xclim-0.60.0.dist-info/WHEEL
xclim-0.60.0.dist-info/METADATA
xclim-0.60.0.dist-info/RECORD
