Metadata-Version: 2.4
Name: xclim
Version: 0.60.0
Summary: Climate indices computation package based on Xarray.
Keywords: xclim,xarray,climate,climatology,bias correction,ensemble,indicators,analysis
Author-email: Travis Logan <logan.travis@ouranos.ca>
Maintainer-email: Trevor James Smith <smith.trevorj@ouranos.ca>, Pascal Bourgault <bourgault.pascal@ouranos.ca>
Requires-Python: >=3.10.0
License-Expression: Apache-2.0
Classifier: Development Status :: 4 - Beta
Classifier: Intended Audience :: Developers
Classifier: Intended Audience :: Science/Research
Classifier: Natural Language :: English
Classifier: Operating System :: OS Independent
Classifier: Programming Language :: Python :: 3
Classifier: Programming Language :: Python :: 3.10
Classifier: Programming Language :: Python :: 3.11
Classifier: Programming Language :: Python :: 3.12
Classifier: Programming Language :: Python :: 3.13
Classifier: Programming Language :: Python :: 3.14
Classifier: Programming Language :: Python :: 3 :: Only
Classifier: Topic :: Scientific/Engineering :: Atmospheric Science
Classifier: Topic :: Scientific/Engineering :: Hydrology
Classifier: Typing :: Typed
License-File: LICENSE
Requires-Dist: boltons >=20.1
Requires-Dist: bottleneck >=1.3.1
Requires-Dist: cf-xarray >=0.9.3
Requires-Dist: cftime >=1.4.1
Requires-Dist: click >=8.1
Requires-Dist: dask[array] >=2024.8.1
Requires-Dist: filelock >=3.14.0
Requires-Dist: numba >=0.57.0
Requires-Dist: numpy >=1.25.0
Requires-Dist: packaging >=24.0
Requires-Dist: pandas >=2.2.0
Requires-Dist: pint >=0.24.4
Requires-Dist: pyarrow >=15.0
Requires-Dist: pyyaml >=6.0.1
Requires-Dist: scikit-learn >=1.2.0
Requires-Dist: scipy >=1.11.0
Requires-Dist: xarray >=2023.11.0,!=2024.10.0
Requires-Dist: yamale >=5.0.0
Requires-Dist: xclim[dev] ; extra == "all"
Requires-Dist: xclim[docs] ; extra == "all"
Requires-Dist: xclim[extras] ; extra == "all"
Requires-Dist: bump-my-version >=1.2.3 ; extra == "dev"
Requires-Dist: codespell >=2.4.1 ; extra == "dev"
Requires-Dist: coverage[toml] >=7.5.0 ; extra == "dev"
Requires-Dist: deptry >=0.23.0 ; extra == "dev"
Requires-Dist: flake8 >=7.3.0 ; extra == "dev"
Requires-Dist: flake8-rst-docstrings >=0.4.0 ; extra == "dev"
Requires-Dist: h5netcdf >=1.5.0 ; extra == "dev"
Requires-Dist: h5py >=3.12.1 ; extra == "dev"
Requires-Dist: ipython >=8.10.0 ; extra == "dev"
Requires-Dist: mypy >=1.14.1 ; extra == "dev"
Requires-Dist: nbconvert >=7.16.4 ; extra == "dev"
Requires-Dist: nbval >=0.11.0 ; extra == "dev"
Requires-Dist: numpydoc >=1.9.0 ; extra == "dev"
Requires-Dist: pandas-stubs >=2.2 ; extra == "dev"
Requires-Dist: pip >=25.0 ; extra == "dev"
Requires-Dist: pooch >=1.8.0 ; extra == "dev"
Requires-Dist: pre-commit >=3.7 ; extra == "dev"
Requires-Dist: pylint >=3.3.1 ; extra == "dev"
Requires-Dist: pytest >=9.0.0 ; extra == "dev"
Requires-Dist: pytest-cov >=5.0.0 ; extra == "dev"
Requires-Dist: pytest-socket >=0.6.0 ; extra == "dev"
Requires-Dist: pytest-timeout >=2.4.0 ; extra == "dev"
Requires-Dist: pytest-xdist[psutil] >=3.2 ; extra == "dev"
Requires-Dist: ruff >=0.13.3 ; extra == "dev"
Requires-Dist: tokenize-rt >=5.2.0 ; extra == "dev"
Requires-Dist: tox >=4.31.0 ; extra == "dev"
Requires-Dist: tox-gh >=1.5.0 ; extra == "dev"
Requires-Dist: vulture >=2.14 ; extra == "dev"
Requires-Dist: xdoctest >=1.3.0 ; extra == "dev"
Requires-Dist: yamllint >=1.35.1 ; extra == "dev"
Requires-Dist: cairosvg >=2.6.0 ; extra == "docs"
Requires-Dist: distributed >=2.0 ; extra == "docs"
Requires-Dist: furo >=2023.9.10 ; extra == "docs"
Requires-Dist: ipykernel ; extra == "docs"
Requires-Dist: matplotlib >=3.7.0 ; extra == "docs"
Requires-Dist: nbsphinx >=0.9.5 ; extra == "docs"
Requires-Dist: nc-time-axis >=1.4.1 ; extra == "docs"
Requires-Dist: pooch >=1.8.0 ; extra == "docs"
Requires-Dist: pybtex >=0.24.0 ; extra == "docs"
Requires-Dist: sphinx >=8.2.0 ; extra == "docs"
Requires-Dist: sphinx-autobuild >=2024.4.16 ; extra == "docs"
Requires-Dist: sphinx-autodoc-typehints >=3.1.0 ; extra == "docs"
Requires-Dist: sphinx-codeautolink >=0.16.2 ; extra == "docs"
Requires-Dist: sphinx-copybutton ; extra == "docs"
Requires-Dist: sphinx-mdinclude ; extra == "docs"
Requires-Dist: sphinxcontrib-bibtex ; extra == "docs"
Requires-Dist: sphinxcontrib-svg2pdfconverter[cairosvg] ; extra == "docs"
Requires-Dist: flox >=0.9 ; extra == "extras"
Requires-Dist: lmoments3 >=1.0.7 ; extra == "extras"
Requires-Dist: numbagg >=0.8 ; extra == "extras"
Requires-Dist: xsdba >=0.4.0 ; extra == "extras"
Requires-Dist: pymannkendall >=1.4.0 ; extra == "extras"
Project-URL: About Ouranos, https://www.ouranos.ca/en/
Project-URL: Changelog, https://xclim.readthedocs.io/en/stable/changelog.html
Project-URL: Homepage, https://xclim.readthedocs.io/
Project-URL: Issue tracker, https://github.com/Ouranosinc/xclim/issues
Project-URL: Mastodon, https://fosstodon.org/@xclim
Project-URL: Source, https://github.com/Ouranosinc/xclim/
Project-URL: Zenodo, https://doi.org/10.5281/zenodo.2795043
Provides-Extra: all
Provides-Extra: dev
Provides-Extra: docs
Provides-Extra: extras
